<?xml version="1.0" encoding="utf-8"?>
<TransitoMaritimo xmlns:xsd="http://www.w3.org/2001/XMLSchema" xmlns:xsi="http://www.w3.org/2001/XMLSchema-instance">
  <barcoLentos>
    <BarcoLento>
      <nombre>barco2</nombre>
      <cantidadPasajeros>18</cantidadPasajeros>
      <cantidadTripulantes>10</cantidadTripulantes>
      <cantidadVehiculos>8</cantidadVehiculos>
    </BarcoLento>
  </barcoLentos>
  <barcoRapidos>
    <BarcoRapido>
      <nombre>barco1</nombre>
      <cantidadPasajeros>12</cantidadPasajeros>
      <cantidadTripulantes>10</cantidadTripulantes>
      <velocidadMax>80</velocidadMax>
    </BarcoRapido>
  </barcoRapidos>
  <cargos>
    <Cargo>
      <nombreCargo>Capitán</nombreCargo>
    </Cargo>
    <Cargo>
      <nombreCargo>Oficial de cubierta</nombreCargo>
    </Cargo>
    <Cargo>
      <nombreCargo>Piloto</nombreCargo>
    </Cargo>
    <Cargo>
      <nombreCargo>Comisario de a bordo</nombreCargo>
    </Cargo>
    <Cargo>
      <nombreCargo>Jefe de maquinas</nombreCargo>
    </Cargo>
    <Cargo>
      <nombreCargo>Servicios</nombreCargo>
    </Cargo>
  </cargos>
  <mantenimientos>
    <Mantenimiento>
      <id>1</id>
      <fechaMantenimiento>2022-10-20T00:00:00-03:00</fechaMantenimiento>
      <descripcion>Mantenimiento 1</descripcion>
      <barcos xsi:type="BarcoRapido">
        <nombre>barco1</nombre>
        <cantidadPasajeros>12</cantidadPasajeros>
        <cantidadTripulantes>10</cantidadTripulantes>
        <velocidadMax>80</velocidadMax>
      </barcos>
      <nombreBarco>barco1</nombreBarco>
      <tipobarco>Barco Rapido</tipobarco>
      <TiposMantenimiento>
        <codigo>2</codigo>
        <precioBase>2000</precioBase>
        <descripcion>Tipo mantenimiento 2</descripcion>
      </TiposMantenimiento>
      <encargados>
        <cedula>18349320</cedula>
        <nombre>Ernesto Santos</nombre>
        <correo>ernesto.santos@ejemplo.com</correo>
        <cantidadPersonal>5</cantidadPersonal>
      </encargados>
      <precio>2800</precio>
      <Terminado>true</Terminado>
    </Mantenimiento>
    <Mantenimiento>
      <id>2</id>
      <fechaMantenimiento>2022-10-20T00:00:00-03:00</fechaMantenimiento>
      <descripcion>Mantenimiento 2</descripcion>
      <barcos xsi:type="BarcoRapido">
        <nombre>barco1</nombre>
        <cantidadPasajeros>12</cantidadPasajeros>
        <cantidadTripulantes>10</cantidadTripulantes>
        <velocidadMax>80</velocidadMax>
      </barcos>
      <nombreBarco>barco1</nombreBarco>
      <tipobarco>Barco Rapido</tipobarco>
      <TiposMantenimiento>
        <codigo>2</codigo>
        <precioBase>2000</precioBase>
        <descripcion>Tipo mantenimiento 2</descripcion>
      </TiposMantenimiento>
      <encargados>
        <cedula>18349320</cedula>
        <nombre>Ernesto Santos</nombre>
        <correo>ernesto.santos@ejemplo.com</correo>
        <cantidadPersonal>5</cantidadPersonal>
      </encargados>
      <precio>2800</precio>
      <Terminado>true</Terminado>
    </Mantenimiento>
    <Mantenimiento>
      <id>3</id>
      <fechaMantenimiento>2022-10-20T00:00:00-03:00</fechaMantenimiento>
      <descripcion>Mantenimiento 3</descripcion>
      <barcos xsi:type="BarcoLento">
        <nombre>barco2</nombre>
        <cantidadPasajeros>18</cantidadPasajeros>
        <cantidadTripulantes>10</cantidadTripulantes>
        <cantidadVehiculos>8</cantidadVehiculos>
      </barcos>
      <nombreBarco>barco2</nombreBarco>
      <tipobarco>Barco Lento</tipobarco>
      <TiposMantenimiento>
        <codigo>2</codigo>
        <precioBase>2000</precioBase>
        <descripcion>Tipo mantenimiento 2</descripcion>
      </TiposMantenimiento>
      <encargados>
        <cedula>18349320</cedula>
        <nombre>Ernesto Santos</nombre>
        <correo>ernesto.santos@ejemplo.com</correo>
        <cantidadPersonal>5</cantidadPersonal>
      </encargados>
      <precio>2000</precio>
      <Terminado>true</Terminado>
    </Mantenimiento>
  </mantenimientos>
  <tiposMantenimiento>
    <Tipo_de_Mantenimiento>
      <codigo>2</codigo>
      <precioBase>2000</precioBase>
      <descripcion>Tipo mantenimiento 2</descripcion>
    </Tipo_de_Mantenimiento>
  </tiposMantenimiento>
  <usuarios>
    <Usuario>
      <cedula>1</cedula>
      <nombre />
      <correo>1</correo>
      <nombreUsuario>1</nombreUsuario>
      <contraseña>12345</contraseña>
      <AsignarTripulacion>false</AsignarTripulacion>
      <BusquedaMant>false</BusquedaMant>
      <IngresarCargos>false</IngresarCargos>
      <IngresarTripulantes>false</IngresarTripulantes>
      <IngresarEncargados>false</IngresarEncargados>
      <IngresoMantenimiento>false</IngresoMantenimiento>

      <IngresoTipoMantenimiento>false</IngresoTipoMantenimiento>
      <IngresoUsuarios>false</IngresoUsuarios>
      <RegistroBarco>false</RegistroBarco>
    </Usuario>
    <Usuario>
      <cedula>1</cedula>
      <nombre>Roberto</nombre>
      <correo>1</correo>
      <nombreUsuario>1</nombreUsuario>
      <contraseña>12345</contraseña>
      <AsignarTripulacion>false</AsignarTripulacion>
      <BusquedaMant>false</BusquedaMant>
      <IngresarCargos>false</IngresarCargos>
      <IngresarTripulantes>false</IngresarTripulantes>
      <IngresarEncargados>false</IngresarEncargados>
      <IngresoMantenimiento>false</IngresoMantenimiento>
      <IngresoTipoMantenimiento>false</IngresoTipoMantenimiento>
      <IngresoUsuarios>false</IngresoUsuarios>
      <RegistroBarco>false</RegistroBarco>
    </Usuario>
    <Usuario>
      <cedula>1</cedula>
      <nombre>Roberto</nombre>
      <correo>1</correo>
      <nombreUsuario>1</nombreUsuario>
      <contraseña>12345</contraseña>
      <AsignarTripulacion>false</AsignarTripulacion>
      <BusquedaMant>false</BusquedaMant>
      <IngresarCargos>false</IngresarCargos>
      <IngresarTripulantes>false</IngresarTripulantes>
      <IngresarEncargados>false</IngresarEncargados>
      <IngresoMantenimiento>false</IngresoMantenimiento>
      <IngresoTipoMantenimiento>false</IngresoTipoMantenimiento>
      <IngresoUsuarios>false</IngresoUsuarios>
      <RegistroBarco>false</RegistroBarco>
    </Usuario>
    <Usuario>
      <cedula>11111</cedula>
      <nombre>Federico Barboza</nombre>
      <correo>fedefedefede</correo>
      <nombreUsuario>BarbozaF</nombreUsuario>
      <contraseña>1234567</contraseña>
      <AsignarTripulacion>false</AsignarTripulacion>
      <BusquedaMant>false</BusquedaMant>
      <IngresarCargos>false</IngresarCargos>
      <IngresarTripulantes>false</IngresarTripulantes>
      <IngresarEncargados>false</IngresarEncargados>
      <IngresoMantenimiento>false</IngresoMantenimiento>
      <IngresoTipoMantenimiento>false</IngresoTipoMantenimiento>
      <IngresoUsuarios>false</IngresoUsuarios>
      <RegistroBarco>false</RegistroBarco>
    </Usuario>
    <Usuario>
      <cedula>11111</cedula>
      <nombre>Roberto</nombre>
      <correo>1</correo>
      <nombreUsuario>Google</nombreUsuario>
      <contraseña>12345</contraseña>
      <AsignarTripulacion>false</AsignarTripulacion>
      <BusquedaMant>false</BusquedaMant>
      <IngresarCargos>false</IngresarCargos>
      <IngresarTripulantes>false</IngresarTripulantes>
      <IngresarEncargados>false</IngresarEncargados>
      <IngresoMantenimiento>false</IngresoMantenimiento>
      <IngresoTipoMantenimiento>false</IngresoTipoMantenimiento>
      <IngresoUsuarios>false</IngresoUsuarios>
      <RegistroBarco>false</RegistroBarco>
    </Usuario>
    <Usuario>
      <cedula>1</cedula>
      <nombre>Jose</nombre>
      <correo>JoseMujica</correo>
      <nombreUsuario>Mujica</nombreUsuario>
      <contraseña>54321</contraseña>
      <AsignarTripulacion>true</AsignarTripulacion>
      <BusquedaMant>true</BusquedaMant>
      <IngresarCargos>false</IngresarCargos>
      <IngresarTripulantes>true</IngresarTripulantes>
      <IngresarEncargados>true</IngresarEncargados>
      <IngresoMantenimiento>true</IngresoMantenimiento>
      <IngresoTipoMantenimiento>true</IngresoTipoMantenimiento>
      <IngresoUsuarios>true</IngresoUsuarios>
      <RegistroBarco>false</RegistroBarco>
    </Usuario>
    <Usuario>
      <cedula>1</cedula>
      <nombre>Administrador</nombre>
      <correo>1</correo>
      <nombreUsuario>Admin</nombreUsuario>
      <contraseña>12345</contraseña>
      <AsignarTripulacion>true</AsignarTripulacion>
      <BusquedaMant>true</BusquedaMant>
      <IngresarCargos>true</IngresarCargos>
      <IngresarTripulantes>true</IngresarTripulantes>
      <IngresarEncargados>true</IngresarEncargados>
      <IngresoMantenimiento>true</IngresoMantenimiento>
      <IngresoTipoMantenimiento>true</IngresoTipoMantenimiento>
      <IngresoUsuarios>true</IngresoUsuarios>
      <RegistroBarco>true</RegistroBarco>
    </Usuario>
    <Usuario>
      <cedula>2</cedula>
      <nombre>Maria</nombre>
      <correo>2</correo>
      <nombreUsuario>Maria</nombreUsuario>
      <contraseña>1</contraseña>
      <AsignarTripulacion>false</AsignarTripulacion>
      <BusquedaMant>true</BusquedaMant>
      <IngresarCargos>false</IngresarCargos>
      <IngresarTripulantes>false</IngresarTripulantes>
      <IngresarEncargados>false</IngresarEncargados>
      <IngresoMantenimiento>false</IngresoMantenimiento>
      <IngresoTipoMantenimiento>false</IngresoTipoMantenimiento>

      <IngresoUsuarios>false</IngresoUsuarios>
      <RegistroBarco>false</RegistroBarco>
    </Usuario>
  </usuarios>
  <tripulantes>
    <Tripulante>
      <cedula>57248903</cedula>
      <nombre>Mario Gimenez</nombre>
      <correo>mario.gimenez@ejemplo.com</correo>
      <fechaIngreso>2022-10-13T00:00:00-03:00</fechaIngreso>
      <Cargo>Jefe de maquinas</Cargo>
    </Tripulante>
    <Tripulante>
      <cedula>52845890</cedula>
      <nombre>Facundo esteves</nombre>
      <correo>facundoesteves@ejemplo.com</correo>
      <fechaIngreso>2022-10-13T00:00:00-03:00</fechaIngreso>
      <Cargo>Capitán</Cargo>
    </Tripulante>
  </tripulantes>
  <encargados>
    <Encargado>
      <cedula>18349320</cedula>
      <nombre>Ernesto Santos</nombre>
      <correo>ernesto.santos@ejemplo.com</correo>
      <cantidadPersonal>5</cantidadPersonal>
    </Encargado>
  </encargados>

  <cantidadTripulantesXtipos />
  <registrosA>
    <RegistroAcceso>
      <usuarios>facundo</usuarios>
      <fechaAcceso>2022-10-24T20:39:39.4462279-03:00</fechaAcceso>
    </RegistroAcceso>
    <RegistroAcceso>
      <usuarios>Juan</usuarios>
      <fechaAcceso>2022-10-24T20:45:14.7456737-03:00</fechaAcceso>
    </RegistroAcceso>
  </registrosA>
  <registrosE>
    <RegistroEgreso>
      <usuarios>facundo</usuarios>
      <fechaEgreso>2022-10-24T20:39:41.2695522-03:00</fechaEgreso>
    </RegistroEgreso>
    <RegistroEgreso>
      <usuarios>Juan</usuarios>
      <fechaEgreso>2022-10-24T20:45:18.4614263-03:00</fechaEgreso>
    </RegistroEgreso>
  </registrosE>
  <registrosC>
    <RegistroCambio>
      <usuarios>facundo</usuarios>
      <fechaCambio>2022-10-24T20:39:42.5913464-03:00</fechaCambio>
      <descripcion>Ingreso de barco</descripcion>
    </RegistroCambio>
    <RegistroCambio>
      <usuarios>facundo</usuarios>
      <fechaCambio>2022-10-24T20:39:47.2053601-03:00</fechaCambio>
      <descripcion>Ingreso de barco</descripcion>
    </RegistroCambio>
    <RegistroCambio>
      <usuarios>facundo</usuarios>
      <fechaCambio>2022-10-24T20:40:12.2224702-03:00</fechaCambio>
      <descripcion>Registro barco</descripcion>
    </RegistroCambio>
    <RegistroCambio>
      <usuarios>facundo</usuarios>
      <fechaCambio>2022-10-24T20:40:18.6533945-03:00</fechaCambio>
      <descripcion>Ingreso usuario</descripcion>
    </RegistroCambio>
    <RegistroCambio>
      <usuarios>facundo</usuarios>
      <fechaCambio>2022-10-24T20:40:27.6340223-03:00</fechaCambio>
      <descripcion>Ingreso usuario</descripcion>
    </RegistroCambio>
    <RegistroCambio>
      <usuarios>Juan</usuarios>
      <fechaCambio>2022-10-24T20:45:20.7402966-03:00</fechaCambio>
      <descripcion>Ingreso tripulantes</descripcion>
    </RegistroCambio>
  </registrosC>

  <cantidadTripulantesXtipos>
    <cantidadTripulantesXtipo>
      <Cargo>Capitán</Cargo>
      <Cantidad>1</Cantidad>
    </cantidadTripulantesXtipo>
    <cantidadTripulantesXtipo>
      <Cargo>Oficial de cubierta</Cargo>
      <Cantidad>0</Cantidad>
    </cantidadTripulantesXtipo>
    <cantidadTripulantesXtipo>
      <Cargo>Piloto</Cargo>
      <Cantidad>0</Cantidad>
    </cantidadTripulantesXtipo>
    <cantidadTripulantesXtipo>
      <Cargo>Comisario de a bordo</Cargo>
      <Cantidad>0</Cantidad>
    </cantidadTripulantesXtipo>
    <cantidadTripulantesXtipo>
      <Cargo>Jefe de maquinas</Cargo>
      <Cantidad>1</Cantidad>
    </cantidadTripulantesXtipo>
    <cantidadTripulantesXtipo>
      <Cargo>Servicios</Cargo>
      <Cantidad>0</Cantidad>
    </cantidadTripulantesXtipo>
    <cantidadTripulantesXtipo>
      <Cargo>Capitán</Cargo>
      <Cantidad>1</Cantidad>
    </cantidadTripulantesXtipo>
    <cantidadTripulantesXtipo>
      <Cargo>Oficial de cubierta</Cargo>
      <Cantidad>0</Cantidad>
    </cantidadTripulantesXtipo>
    <cantidadTripulantesXtipo>
      <Cargo>Piloto</Cargo>
      <Cantidad>0</Cantidad>
    </cantidadTripulantesXtipo>
    <cantidadTripulantesXtipo>
      <Cargo>Comisario de a bordo</Cargo>
      <Cantidad>0</Cantidad>
    </cantidadTripulantesXtipo>
    <cantidadTripulantesXtipo>
      <Cargo>Jefe de maquinas</Cargo>
      <Cantidad>1</Cantidad>
    </cantidadTripulantesXtipo>
    <cantidadTripulantesXtipo>
      <Cargo>Servicios</Cargo>
      <Cantidad>0</Cantidad>
    </cantidadTripulantesXtipo>
  </cantidadTripulantesXtipos>
  <idUsuario />

</TransitoMaritimo>